wordleaisql/__init__.py
wordleaisql/api.py
wordleaisql/approx.py
wordleaisql/base.py
wordleaisql/bigquery.py
wordleaisql/sqlite.py
wordleaisql/utils.py
wordleaisql/wordle-judge-all.cpp
wordleaisql/wordle-vocab.txt
wordleaisql-0.2.10.dist-info/LICENSE
wordleaisql-0.2.10.dist-info/METADATA
wordleaisql-0.2.10.dist-info/WHEEL
wordleaisql-0.2.10.dist-info/entry_points.txt
wordleaisql-0.2.10.dist-info/top_level.txt
wordleaisql-0.2.10.dist-info/RECORD
