Metadata-Version: 2.1
Name: wordleaisql
Version: 0.2.10
Summary: Wordle AI with SQL Backend
Home-page: https://github.com/kota7/wordleai-sql
License: UNKNOWN
Platform: UNKNOWN
Classifier: Development Status :: 3 - Alpha
Classifier: Programming Language :: Python :: 3.5
Classifier: Programming Language :: Python :: 3.6
Classifier: Programming Language :: Python :: 3.7
Classifier: Programming Language :: Python :: 3.8
Classifier: Programming Language :: Python :: 3.9
License-File: LICENSE
Requires-Dist: tqdm
